eotdl_cli/__init__.py
eotdl_cli/commands/__init__.py
eotdl_cli/commands/auth.py
eotdl_cli/commands/datasets.py
eotdl_cli/main.py
eotdl_cli/src/__init__.py
eotdl_cli/src/errors/__init__.py
eotdl_cli/src/errors/auth.py
eotdl_cli/src/repos/APIRepo.py
eotdl_cli/src/repos/AuthRepo.py
eotdl_cli/src/repos/__init__.py
eotdl_cli/src/usecases/__init__.py
eotdl_cli/src/usecases/auth/Auth.py
eotdl_cli/src/usecases/auth/IsLogged.py
eotdl_cli/src/usecases/auth/Logout.py
eotdl_cli/src/usecases/auth/__init__.py
eotdl_cli/src/usecases/auth/main.py
eotdl_cli/src/usecases/datasets/DownloadDataset.py
eotdl_cli/src/usecases/datasets/IngestDataset.py
eotdl_cli/src/usecases/datasets/IngestLargeDataset.py
eotdl_cli/src/usecases/datasets/IngestLargeDatasetParallel.py
eotdl_cli/src/usecases/datasets/RetrieveDataset.py
eotdl_cli/src/usecases/datasets/RetrieveDatasets.py
eotdl_cli/src/usecases/datasets/UpdateDataset.py
eotdl_cli/src/usecases/datasets/__init__.py
eotdl_cli/src/usecases/datasets/main.py
eotdl_cli/src/utils.py
eotdl_cli-2023.6.14.post2.dist-info/entry_points.txt
eotdl_cli-2023.6.14.post2.dist-info/WHEEL
eotdl_cli-2023.6.14.post2.dist-info/METADATA
eotdl_cli-2023.6.14.post2.dist-info/RECORD
