Metadata-Version: 2.1
Name: eotdl-cli
Version: 2023.6.14.post2
Summary: 
License: MIT
Author: EarthPulse
Author-email: it@earthpulse.es
Requires-Python: >=3.8,<4.0
Classifier: License :: OSI Approved :: MIT License
Classifier: Programming Language :: Python :: 3
Classifier: Programming Language :: Python :: 3.8
Classifier: Programming Language :: Python :: 3.9
Classifier: Programming Language :: Python :: 3.10
Requires-Dist: pydantic (>=1.10.6,<2.0.0)
Requires-Dist: pyjwt (>=2.6.0,<3.0.0)
Requires-Dist: requests (>=2.28.2,<3.0.0)
Requires-Dist: tqdm (>=4.65.0,<5.0.0)
Requires-Dist: typer[all] (>=0.7.0,<0.8.0)
